{
   "apps" : [
      {
         "desc" : "Hello World Sample App in Clojure",
         "framework" : "clojure",
         "home" : "https://github.com/Stackato-Apps/hello-clojure#readme",
         "id" : "hello-clojure",
         "license" : "Unknown",
         "mem" : "128",
         "name" : "Hello Clojure",
         "repo" : "git://github.com/Stackato-Apps/hello-clojure.git"
      },
      {
         "desc" : "Live Video Game Editor in Clojure",
         "framework" : "clojure",
         "home" : "https://github.com/Stackato-Apps/live-game-editor#readme",
         "id" : "live-game-editor",
         "license" : "Unknown",
         "mem" : "128",
         "name" : "Live Game Editor",
         "repo" : "git://github.com/Stackato-Apps/live-game-editor.git"
      },
      {
         "desc" : "Simple Sample App to Print Environment Variables",
         "framework" : "node",
         "home" : "https://github.com/Stackato-Apps/node-env#readme",
         "id" : "env",
         "license" : "Unknown",
         "mem" : "128",
         "name" : "Env",
         "repo" : "git://github.com/Stackato-Apps/node-env.git",
         "runtime" : "node"
      },
      {
         "desc" : "A Multiplayer Minesweeper-style Game",
         "framework" : "node",
         "home" : "https://github.com/Stackato-Apps/multisweeper#readme",
         "id" : "multisweeper",
         "license" : "Unknown",
         "mem" : "128",
         "name" : "MultiSweeper",
         "repo" : "git://github.com/Stackato-Apps/multisweeper.git",
         "runtime" : "node",
         "services" : {
            "redis" : "redis-multisweeper"
         }
      },
      {
         "desc" : "Beautiful IDE for Node.JS",
         "framework" : "node",
         "home" : "https://github.com/Stackato-Apps/Nide#readme",
         "id" : "nide",
         "license" : "Unknown",
         "mem" : "128",
         "name" : "Nide",
         "repo" : "git://github.com/Stackato-Apps/nide.git",
         "runtime" : "node",
         "services" : {
            "filesystem" : "fs-nide"
         }
      },
      {
         "desc" : "A web based irc client, built on top of node.js and socket.io",
         "framework" : "node",
         "home" : "https://github.com/Stackato-Apps/subway#readme",
         "id" : "subway",
         "license" : "MIT",
         "mem" : "128",
         "name" : "Subway",
         "repo" : "git://github.com/Stackato-Apps/subway.git"
      },
      {
         "desc" : "A terminal in your browser using node.js and socket.io. Based on Fabrice Bellards vt100 for jslinux.",
         "framework" : "node",
         "home" : "https://github.com/Stackato-Apps/tty.js#readme",
         "id" : "tty-js",
         "license" : "MIT",
         "mem" : "128",
         "name" : "tty-js",
         "repo" : "git://github.com/Stackato-Apps/tty.js.git"
      },
      {
         "desc" : "Perl::Critic Website",
         "framework" : "perl",
         "home" : "https://github.com/ActiveState/perlcritic.com#readme",
         "id" : "perlcritic",
         "license" : "Unknown",
         "mem" : "128",
         "name" : "Perl::Critic",
         "repo" : "git://github.com/ActiveState/perlcritic.com.git"
      },
      {
         "desc" : "A Photo Booth App",
         "framework" : "perl",
         "home" : "https://github.com/Stackato-Apps/photobooth#readme",
         "id" : "photobooth",
         "license" : "Unknown",
         "mem" : "128",
         "name" : "Photo Booth",
         "repo" : "git://github.com/Stackato-Apps/photobooth.git"
      },
      {
         "desc" : "Bottle Currency Converter",
         "framework" : "python",
         "home" : "https://github.com/Stackato-Apps/bottle-currency#readme",
         "id" : "currency",
         "license" : "Unknown",
         "mem" : "128",
         "name" : "Currency Converter",
         "repo" : "git://github.com/Stackato-Apps/bottle-currency.git",
         "services" : {
            "redis" : "redis-currency"
         }
      },
      {
         "desc" : "Vanilla Mezzanine CMS",
         "env" : {
            "DJANGO_SETTINGS_MODULE" : "settings"
         },
         "framework" : "python",
         "home" : "https://github.com/Stackato-Apps/mezzanine#readme",
         "id" : "mezzanine",
         "license" : "Unknown",
         "mem" : "128",
         "name" : "Mezzanine",
         "repo" : "git://github.com/Stackato-Apps/mezzanine.git"
      },
      {
         "desc" : "Twitter Activity for the American 2012 Presidential Election",
         "framework" : "rails3",
         "home" : "https://github.com/Stackato-Apps/prezbuzz#readme",
         "id" : "prezbuzz",
         "license" : "Unknown",
         "mem" : "256",
         "name" : "Prez Buzz",
         "repo" : "git://github.com/Stackato-Apps/prezbuzz.git",
         "runtime" : "ruby19",
         "services" : {
            "mysql" : "mysql-prezbuzz"
         }
      }
   ],
   "store" : {
      "contact" : "Stackato Support <stackato-support@activestate.com>",
      "icon" : "activestate.png",
      "icons" : "http://get.stackato.com/store/icon/",
      "title" : "ActiveState Sample Stackato Applications"
   }
}
